{
"meta":{"test_sets":[],"test_metrics":[],"learn_metrics":[{"best_value":"Min","name":"RMSE"}],"launch_mode":"Train","parameters":"","iteration_count":100,"learn_sets":["learn"],"name":"experiment"},
"iterations":[
{"learn":[14.005006],"iteration":0,"passed_time":0.0009183170867,"remaining_time":0.09091339158},
{"learn":[13.14441192],"iteration":1,"passed_time":0.001652113878,"remaining_time":0.08095358},
{"learn":[12.34258257],"iteration":2,"passed_time":0.002345379511,"remaining_time":0.07583393753},
{"learn":[11.64527793],"iteration":3,"passed_time":0.002908468275,"remaining_time":0.06980323859},
{"learn":[11.02766183],"iteration":4,"passed_time":0.003650243863,"remaining_time":0.0693546334},
{"learn":[10.43485794],"iteration":5,"passed_time":0.004432839548,"remaining_time":0.06944781959},
{"learn":[9.890641275],"iteration":6,"passed_time":0.005219741755,"remaining_time":0.0693479976},
{"learn":[9.492161212],"iteration":7,"passed_time":0.005991730636,"remaining_time":0.06890490232},
{"learn":[9.105082953],"iteration":8,"passed_time":0.006819818288,"remaining_time":0.06895594046},
{"learn":[8.674157135],"iteration":9,"passed_time":0.007540062521,"remaining_time":0.06786056269},
{"learn":[8.341743544],"iteration":10,"passed_time":0.008256337189,"remaining_time":0.06680127362},
{"learn":[8.049372916],"iteration":11,"passed_time":0.008972570102,"remaining_time":0.06579884742},
{"learn":[7.757318612],"iteration":12,"passed_time":0.009678155711,"remaining_time":0.06476919591},
{"learn":[7.522206899],"iteration":13,"passed_time":0.01041881855,"remaining_time":0.06400131396},
{"learn":[7.297756655],"iteration":14,"passed_time":0.01121086904,"remaining_time":0.06352825791},
{"learn":[7.088359431],"iteration":15,"passed_time":0.01199386306,"remaining_time":0.06296778108},
{"learn":[6.882113791],"iteration":16,"passed_time":0.01267458241,"remaining_time":0.06188178473},
{"learn":[6.704728832],"iteration":17,"passed_time":0.01334870294,"remaining_time":0.06081075784},
{"learn":[6.563881962],"iteration":18,"passed_time":0.01407876733,"remaining_time":0.06002000809},
{"learn":[6.418790279],"iteration":19,"passed_time":0.0148698508,"remaining_time":0.05947940318},
{"learn":[6.315756953],"iteration":20,"passed_time":0.01556108133,"remaining_time":0.05853930596},
{"learn":[6.210157751],"iteration":21,"passed_time":0.01626147273,"remaining_time":0.05765431239},
{"learn":[6.115058449],"iteration":22,"passed_time":0.01693044664,"remaining_time":0.05668019092},
{"learn":[6.014819884],"iteration":23,"passed_time":0.01766659502,"remaining_time":0.05594421757},
{"learn":[5.93117229],"iteration":24,"passed_time":0.01834230471,"remaining_time":0.05502691414},
{"learn":[5.844857622],"iteration":25,"passed_time":0.01902506584,"remaining_time":0.05414826431},
{"learn":[5.771145213],"iteration":26,"passed_time":0.01968939753,"remaining_time":0.05323429702},
{"learn":[5.704018229],"iteration":27,"passed_time":0.02042326739,"remaining_time":0.05251697328},
{"learn":[5.665806474],"iteration":28,"passed_time":0.02121905738,"remaining_time":0.051950106},
{"learn":[5.616500369],"iteration":29,"passed_time":0.02195523499,"remaining_time":0.05122888165},
{"learn":[5.558023666],"iteration":30,"passed_time":0.02274302781,"remaining_time":0.05062157804},
{"learn":[5.510080976],"iteration":31,"passed_time":0.02345438384,"remaining_time":0.04984056567},
{"learn":[5.468747792],"iteration":32,"passed_time":0.02414221142,"remaining_time":0.049016005},
{"learn":[5.429275534],"iteration":33,"passed_time":0.02482766151,"remaining_time":0.04819487235},
{"learn":[5.402117324],"iteration":34,"passed_time":0.02553853445,"remaining_time":0.04742870683},
{"learn":[5.367635151],"iteration":35,"passed_time":0.02622423423,"remaining_time":0.04662086086},
{"learn":[5.345181232],"iteration":36,"passed_time":0.02699652667,"remaining_time":0.04596705892},
{"learn":[5.319151269],"iteration":37,"passed_time":0.02771683395,"remaining_time":0.04522220276},
{"learn":[5.296134146],"iteration":38,"passed_time":0.02843099001,"remaining_time":0.04446898438},
{"learn":[5.269629003],"iteration":39,"passed_time":0.02915080668,"remaining_time":0.04372621002},
{"learn":[5.251147059],"iteration":40,"passed_time":0.02985199725,"remaining_time":0.04295775214},
{"learn":[5.248003302],"iteration":41,"passed_time":0.03016331943,"remaining_time":0.04165410779},
{"learn":[5.232376509],"iteration":42,"passed_time":0.03089512413,"remaining_time":0.04095400176},
{"learn":[5.213524255],"iteration":43,"passed_time":0.03158532334,"remaining_time":0.04019950243},
{"learn":[5.189691584],"iteration":44,"passed_time":0.03229741383,"remaining_time":0.0394746169},
{"learn":[5.166052198],"iteration":45,"passed_time":0.0329886001,"remaining_time":0.03872574795},
{"learn":[5.140406659],"iteration":46,"passed_time":0.03364965075,"remaining_time":0.03794535085},
{"learn":[5.118929684],"iteration":47,"passed_time":0.03434298194,"remaining_time":0.0372048971},
{"learn":[5.108792602],"iteration":48,"passed_time":0.03501181723,"remaining_time":0.03644087099},
{"learn":[5.098141225],"iteration":49,"passed_time":0.03597998207,"remaining_time":0.03597998207},
{"learn":[5.085926393],"iteration":50,"passed_time":0.03687083078,"remaining_time":0.03542491585},
{"learn":[5.067816804],"iteration":51,"passed_time":0.03759087126,"remaining_time":0.03469926578},
{"learn":[5.049834901],"iteration":52,"passed_time":0.03833602225,"remaining_time":0.0339960952},
{"learn":[5.03838627],"iteration":53,"passed_time":0.03901431903,"remaining_time":0.03323441991},
{"learn":[5.033534248],"iteration":54,"passed_time":0.03947075687,"remaining_time":0.03229425562},
{"learn":[5.023726885],"iteration":55,"passed_time":0.04012650975,"remaining_time":0.03152797195},
{"learn":[5.01290392],"iteration":56,"passed_time":0.04084325415,"remaining_time":0.03081157769},
{"learn":[5.005569127],"iteration":57,"passed_time":0.04156074554,"remaining_time":0.03009571229},
{"learn":[4.989969032],"iteration":58,"passed_time":0.04235671424,"remaining_time":0.02943432684},
{"learn":[4.976762446],"iteration":59,"passed_time":0.04309934244,"remaining_time":0.02873289496},
{"learn":[4.967222715],"iteration":60,"passed_time":0.04377231306,"remaining_time":0.0279855772},
{"learn":[4.954407599],"iteration":61,"passed_time":0.04452116222,"remaining_time":0.02728716394},
{"learn":[4.942125056],"iteration":62,"passed_time":0.04526310399,"remaining_time":0.02658309282},
{"learn":[4.930230716],"iteration":63,"passed_time":0.0460151916,"remaining_time":0.02588354527},
{"learn":[4.921695642],"iteration":64,"passed_time":0.04676952391,"remaining_time":0.0251835898},
{"learn":[4.906405625],"iteration":65,"passed_time":0.04755492088,"remaining_time":0.02449798954},
{"learn":[4.894330248],"iteration":66,"passed_time":0.04827835304,"remaining_time":0.0237788903},
{"learn":[4.88211557],"iteration":67,"passed_time":0.04901729853,"remaining_time":0.02306696402},
{"learn":[4.877946398],"iteration":68,"passed_time":0.04979895726,"remaining_time":0.02237344456},
{"learn":[4.863182126],"iteration":69,"passed_time":0.05065089779,"remaining_time":0.02170752762},
{"learn":[4.84646533],"iteration":70,"passed_time":0.05167314468,"remaining_time":0.02110593233},
{"learn":[4.838014752],"iteration":71,"passed_time":0.05242245689,"remaining_time":0.02038651101},
{"learn":[4.82981137],"iteration":72,"passed_time":0.0531788552,"remaining_time":0.01966889165},
{"learn":[4.817094767],"iteration":73,"passed_time":0.05398724283,"remaining_time":0.01896849072},
{"learn":[4.808314151],"iteration":74,"passed_time":0.05483270438,"remaining_time":0.01827756813},
{"learn":[4.796235023],"iteration":75,"passed_time":0.0556349696,"remaining_time":0.01756893777},
{"learn":[4.784434534],"iteration":76,"passed_time":0.05635124051,"remaining_time":0.01683218872},
{"learn":[4.774402487],"iteration":77,"passed_time":0.05707700798,"remaining_time":0.01609864328},
{"learn":[4.76731896],"iteration":78,"passed_time":0.05790835454,"remaining_time":0.01539336007},
{"learn":[4.75934113],"iteration":79,"passed_time":0.05862275946,"remaining_time":0.01465568986},
{"learn":[4.754106378],"iteration":80,"passed_time":0.059380387,"remaining_time":0.01392873275},
{"learn":[4.744002932],"iteration":81,"passed_time":0.0600949556,"remaining_time":0.01319157562},
{"learn":[4.731700554],"iteration":82,"passed_time":0.06083272321,"remaining_time":0.01245971439},
{"learn":[4.723284153],"iteration":83,"passed_time":0.06158782296,"remaining_time":0.0117310139},
{"learn":[4.712232782],"iteration":84,"passed_time":0.06239396088,"remaining_time":0.01101069898},
{"learn":[4.703046867],"iteration":85,"passed_time":0.06316088498,"remaining_time":0.01028200453},
{"learn":[4.698601855],"iteration":86,"passed_time":0.06388444283,"remaining_time":0.009545951227},
{"learn":[4.692429407],"iteration":87,"passed_time":0.0648583806,"remaining_time":0.008844324627},
{"learn":[4.675027364],"iteration":88,"passed_time":0.06561868709,"remaining_time":0.008110174809},
{"learn":[4.662368584],"iteration":89,"passed_time":0.06632518795,"remaining_time":0.007369465328},
{"learn":[4.646206172],"iteration":90,"passed_time":0.06705965865,"remaining_time":0.006632273932},
{"learn":[4.641245848],"iteration":91,"passed_time":0.06788273497,"remaining_time":0.005902846519},
{"learn":[4.633900435],"iteration":92,"passed_time":0.06855267841,"remaining_time":0.00515987902},
{"learn":[4.624738236],"iteration":93,"passed_time":0.06935282879,"remaining_time":0.004426776306},
{"learn":[4.612798287],"iteration":94,"passed_time":0.07007722756,"remaining_time":0.003688275135},
{"learn":[4.605222001],"iteration":95,"passed_time":0.07075251094,"remaining_time":0.002948021289},
{"learn":[4.601725912],"iteration":96,"passed_time":0.07158205247,"remaining_time":0.002213877911},
{"learn":[4.59722371],"iteration":97,"passed_time":0.07237153174,"remaining_time":0.001476970036},
{"learn":[4.580235665],"iteration":98,"passed_time":0.07309448081,"remaining_time":0.000738328089},
{"learn":[4.57591791],"iteration":99,"passed_time":0.07375819871,"remaining_time":0}
]}